MANIFEST.in
README.md
setup.py
ThreatPlaybook.egg-info/PKG-INFO
ThreatPlaybook.egg-info/SOURCES.txt
ThreatPlaybook.egg-info/dependency_links.txt
ThreatPlaybook.egg-info/entry_points.txt
ThreatPlaybook.egg-info/requires.txt
ThreatPlaybook.egg-info/top_level.txt
docs/keywords.html
threat_playbook/ThreatPlaybook.py
threat_playbook/__init__.py
threat_playbook/models.py
threat_playbook/repo.json
threat_playbook/utils.py
threat_playbook/repo/aws_s3.yaml
threat_playbook/repo/cert_validation.yaml
threat_playbook/repo/code_injection.yaml
threat_playbook/repo/idor_pk.yaml
threat_playbook/repo/insecure_deserialization.yaml
threat_playbook/repo/password-bruteforce.yaml
threat_playbook/repo/plaintext-transmission.yaml
threat_playbook/repo/sql_injection.yaml
threat_playbook/repo/weak-default-password.yaml
threat_playbook/repo/xss.yaml
threat_playbook/repo/xxe.yaml