Metadata-Version: 2.1
Name: ThreatPlaybook
Version: 1.2.3
Summary: Threat-Models-as Code, An Action-Oriented Threat Modeling and Automation Framework
Home-page: https://we45.gitbook.io/threatplaybook/
Author: we45
Author-email: info@we45.com
License: MIT License
Platform: UNKNOWN
